LICENSE
MANIFEST.in
README.rst
pyproject.toml
setup.cfg
setup.py
djangocms_pdfembed/__init__.py
djangocms_pdfembed/admin.py
djangocms_pdfembed/apps.py
djangocms_pdfembed/cms_plugins.py
djangocms_pdfembed/models.py
djangocms_pdfembed/tests.py
djangocms_pdfembed/views.py
djangocms_pdfembed.egg-info/PKG-INFO
djangocms_pdfembed.egg-info/SOURCES.txt
djangocms_pdfembed.egg-info/dependency_links.txt
djangocms_pdfembed.egg-info/requires.txt
djangocms_pdfembed.egg-info/top_level.txt
djangocms_pdfembed/migrations/0001_initial.py
djangocms_pdfembed/migrations/__init__.py
djangocms_pdfembed/templates/djangocms_pdfembed/pdf_embed.html